gmymaps/__init__.py
gmymaps/api.py
gmymaps/cookies.py
gmymaps-0.1.1.dist-info/METADATA
gmymaps-0.1.1.dist-info/WHEEL
gmymaps-0.1.1.dist-info/RECORD
