Metadata-Version: 2.1
Name: gmymaps
Version: 0.1.1
Summary: Reverse engineered APIs to interact with a Google My Maps map
Author: heyzec
Author-email: 61238538+heyzec@users.noreply.github.com
Requires-Python: >=3.11,<4.0
Classifier: Programming Language :: Python :: 3
Classifier: Programming Language :: Python :: 3.11
Classifier: Programming Language :: Python :: 3.12
Requires-Dist: lxml (>=5.2.2,<6.0.0)
Requires-Dist: requests (>=2.32.3,<3.0.0)
